mcp_server_rememberizer/__init__.py
mcp_server_rememberizer/server.py
mcp_server_rememberizer/utils.py
mseep_rememberizer_mcp_ea_ck-0.1.5.dist-info/licenses/LICENSE
mseep_rememberizer_mcp_ea_ck-0.1.5.dist-info/METADATA
mseep_rememberizer_mcp_ea_ck-0.1.5.dist-info/WHEEL
mseep_rememberizer_mcp_ea_ck-0.1.5.dist-info/entry_points.txt
mseep_rememberizer_mcp_ea_ck-0.1.5.dist-info/top_level.txt
mseep_rememberizer_mcp_ea_ck-0.1.5.dist-info/RECORD
