Metadata-Version: 2.4
Name: mseep-rememberizer-mcp-ea-ck
Version: 0.1.5
Summary: This is the public ck for testing purpose
Author-email: mseep <support@skydeck.ai>
Requires-Python: >=3.11
License-File: LICENSE
Requires-Dist: httpx>=0.27.2
Requires-Dist: mcp>=1.0.0
Requires-Dist: python-dotenv>=1.0.1
Dynamic: license-file
